fastapi-websocket-validation/__init__.py
fastapi-websocket-validation/handler.py
fastapi_websocket_validation/__init__.py
fastapi_websocket_validation/handler.py
fastapi_websocket_validation-0.1.3.dist-info/licenses/LICENSE
fastapi_websocket_validation-0.1.3.dist-info/METADATA
fastapi_websocket_validation-0.1.3.dist-info/WHEEL
fastapi_websocket_validation-0.1.3.dist-info/top_level.txt
fastapi_websocket_validation-0.1.3.dist-info/RECORD
