Metadata-Version: 2.4
Name: fastapi-websocket-validation
Version: 0.1.3
Summary: A FastAPI WebSocket message validation and handling library
Home-page: https://github.com/zyx-db/fastapi-websocket-validation
Author: Dhiraj Bomma
Author-email: Dhiraj Bomma <dhirajbomma@gmail.com>
Project-URL: Homepage, https://github.com/zyx-db/fastapi-websocket-validation
Project-URL: Bug Tracker, https://github.com/zyx-db/fastapi-websocket-validation/issues
Classifier: Development Status :: 3 - Alpha
Classifier: Intended Audience :: Developers
Classifier: License :: OSI Approved :: MIT License
Classifier: Programming Language :: Python :: 3
Classifier: Programming Language :: Python :: 3.8
Classifier: Programming Language :: Python :: 3.9
Classifier: Programming Language :: Python :: 3.10
Classifier: Programming Language :: Python :: 3.11
Classifier: Programming Language :: Python :: 3.12
Requires-Python: >=3.8
License-File: LICENSE
Requires-Dist: fastapi>=0.115.0
Requires-Dist: pydantic>=2.0.0
Dynamic: author
Dynamic: home-page
Dynamic: license-file
Dynamic: requires-python
